vidfilter_scripter/__init__.py
vidfilter_scripter/res/brightness.svg
vidfilter_scripter/res/contrast.svg
vidfilter_scripter/res/gamma.svg
vidfilter_scripter/res/main_window.ui
vidfilter_scripter/res/make_dialog.ui
vidfilter_scripter/res/saturation.svg
vidfilter_scripter/res/style.css
vidfilter_scripter-1.1.3.dist-info/entry_points.txt
vidfilter_scripter-1.1.3.dist-info/LICENSE
vidfilter_scripter-1.1.3.dist-info/WHEEL
vidfilter_scripter-1.1.3.dist-info/METADATA
vidfilter_scripter-1.1.3.dist-info/RECORD
