Metadata-Version: 2.1
Name: vidfilter_scripter
Version: 1.1.3
Summary: An mpv front-end which creates a mencoder script with video adjustments.
Author-email: Leon Dionne <ldionne@dridesign.sh.cn>
Classifier: License :: OSI Approved :: GNU General Public License v3 or later (GPLv3+)
Requires-Dist: python-mpv >= 1.0.7
Project-URL: Home, https://github.com/Zen-Master-SoSo/vidfilter_scripter
